odoo10_addon_l10n_it_vat_registries_split_payment-10.0.1.0.0.99.dev5-py3.8-nspkg.pth
odoo/addons/l10n_it_vat_registries_split_payment/README.rst
odoo/addons/l10n_it_vat_registries_split_payment/__init__.py
odoo/addons/l10n_it_vat_registries_split_payment/__manifest__.py
odoo/addons/l10n_it_vat_registries_split_payment/i18n/l10n_it_vat_registries_split_payment.pot
odoo/addons/l10n_it_vat_registries_split_payment/models/__init__.py
odoo/addons/l10n_it_vat_registries_split_payment/models/account_tax.py
odoo/addons/l10n_it_vat_registries_split_payment/readme/CONTRIBUTORS.rst
odoo/addons/l10n_it_vat_registries_split_payment/readme/DESCRIPTION.rst
odoo/addons/l10n_it_vat_registries_split_payment/static/description/icon.png
odoo/addons/l10n_it_vat_registries_split_payment/static/description/index.html
odoo/addons/l10n_it_vat_registries_split_payment/tests/__init__.py
odoo/addons/l10n_it_vat_registries_split_payment/tests/test_sp.py
odoo10_addon_l10n_it_vat_registries_split_payment-10.0.1.0.0.99.dev5.dist-info/METADATA
odoo10_addon_l10n_it_vat_registries_split_payment-10.0.1.0.0.99.dev5.dist-info/WHEEL
odoo10_addon_l10n_it_vat_registries_split_payment-10.0.1.0.0.99.dev5.dist-info/namespace_packages.txt
odoo10_addon_l10n_it_vat_registries_split_payment-10.0.1.0.0.99.dev5.dist-info/top_level.txt
odoo10_addon_l10n_it_vat_registries_split_payment-10.0.1.0.0.99.dev5.dist-info/RECORD
