Metadata-Version: 2.1
Name: odoo10-addon-l10n-it-vat-registries-split-payment
Version: 10.0.1.0.0.99.dev5
Summary: Bridge module to make VAT registries work with Split Payment
Home-page: https://github.com/OCA/l10n-italy/
Author: Agile Business Group, Odoo Community Association (OCA)
Author-email: support@odoo-community.org
License: AGPL-3
Platform: UNKNOWN
Classifier: Programming Language :: Python
Classifier: Framework :: Odoo
Classifier: Framework :: Odoo :: 10.0
Classifier: License :: OSI Approved :: GNU Affero General Public License v3
Classifier: Development Status :: 4 - Beta
Requires-Python: ~=2.7
Requires-Dist: odoo10-addon-l10n-it-split-payment
Requires-Dist: odoo10-addon-l10n-it-vat-registries
Requires-Dist: odoo <10.1dev,>=10.0
